instaBasic/__init__.py
instaBasic/api.py
instabasic-0.1.7.dist-info/LICENSE
instabasic-0.1.7.dist-info/METADATA
instabasic-0.1.7.dist-info/WHEEL
instabasic-0.1.7.dist-info/top_level.txt
instabasic-0.1.7.dist-info/RECORD
