Metadata-Version: 2.1
Name: instabasic
Version: 0.1.7
Summary: A Python wrapper for the Instagram Basic Display API
Home-page: https://github.com/ChaseRun/instabasic
Author: Chase Austin
Author-email: chase7867@gmail.com
License: MIT
Project-URL: Instagram Basic Display API, https://developers.facebook.com/docs/instagram-basic-display-api
Keywords: Instagram,Facebook,Meta,API,SDK,Wrapper
Platform: UNKNOWN
Classifier: License :: OSI Approved :: MIT License
Classifier: Operating System :: OS Independent
Classifier: Programming Language :: Python :: 3
Classifier: Programming Language :: Python :: 3.9
License-File: LICENSE
Requires-Dist: requests
